odoo/addons/sale_expense_cost_reinvoice/README.rst
odoo/addons/sale_expense_cost_reinvoice/__init__.py
odoo/addons/sale_expense_cost_reinvoice/__manifest__.py
odoo/addons/sale_expense_cost_reinvoice/i18n/it.po
odoo/addons/sale_expense_cost_reinvoice/i18n/sale_expense_cost_reinvoice.pot
odoo/addons/sale_expense_cost_reinvoice/models/__init__.py
odoo/addons/sale_expense_cost_reinvoice/models/account_move_line.py
odoo/addons/sale_expense_cost_reinvoice/models/sale_order_line.py
odoo/addons/sale_expense_cost_reinvoice/readme/CONTRIBUTORS.rst
odoo/addons/sale_expense_cost_reinvoice/readme/DESCRIPTION.rst
odoo/addons/sale_expense_cost_reinvoice/static/description/icon.png
odoo/addons/sale_expense_cost_reinvoice/static/description/index.html
odoo/addons/sale_expense_cost_reinvoice/tests/__init__.py
odoo/addons/sale_expense_cost_reinvoice/tests/test_sale_expense_cost_reinvoice.py
odoo_addon_sale_expense_cost_reinvoice-15.0.1.0.0.6.dist-info/METADATA
odoo_addon_sale_expense_cost_reinvoice-15.0.1.0.0.6.dist-info/WHEEL
odoo_addon_sale_expense_cost_reinvoice-15.0.1.0.0.6.dist-info/top_level.txt
odoo_addon_sale_expense_cost_reinvoice-15.0.1.0.0.6.dist-info/RECORD
